<profile>

<ReportVersion>
<Version>2023.2.1</Version>
</ReportVersion>

<UserAssignments>
<unit>ns</unit>
<ProductFamily>zynquplus</ProductFamily>
<Part>xczu3eg-sbva484-1-e</Part>
<TopModelName>main_func_Pipeline_VITIS_LOOP_12_1_VITIS_LOOP_13_2_VITIS_LOOP_14_3</TopModelName>
<TargetClockPeriod>10.00</TargetClockPeriod>
<ClockUncertainty>2.70</ClockUncertainty>
<FlowTarget>vivado</FlowTarget>
</UserAssignments>

<PerformanceEstimates>
<PipelineType>no</PipelineType>
<SummaryOfTimingAnalysis>
<unit>ns</unit>
<EstimatedClockPeriod>5.120</EstimatedClockPeriod>
</SummaryOfTimingAnalysis>
<SummaryOfOverallLatency>
<unit>clock cycles</unit>
<Best-caseLatency>153606</Best-caseLatency>
<Average-caseLatency>153606</Average-caseLatency>
<Worst-caseLatency>153606</Worst-caseLatency>
<Best-caseRealTimeLatency>1.536 ms</Best-caseRealTimeLatency>
<Average-caseRealTimeLatency>1.536 ms</Average-caseRealTimeLatency>
<Worst-caseRealTimeLatency>1.536 ms</Worst-caseRealTimeLatency>
<Interval-min>153606</Interval-min>
<Interval-max>153606</Interval-max>
</SummaryOfOverallLatency>
<SummaryOfLoopLatency>
<VITIS_LOOP_12_1_VITIS_LOOP_13_2_VITIS_LOOP_14_3>
<Slack>7.30</Slack>
<TripCount>153600</TripCount>
<Latency>153604</Latency>
<AbsoluteTimeLatency>1536040</AbsoluteTimeLatency>
<PipelineII>1</PipelineII>
<PipelineDepth>6</PipelineDepth>
<InstanceList>
</InstanceList>
</VITIS_LOOP_12_1_VITIS_LOOP_13_2_VITIS_LOOP_14_3>
</SummaryOfLoopLatency>
<SummaryOfViolations>
<IssueType>-</IssueType>
<ViolationType>-</ViolationType>
<SourceLocation>ultra96ms2_418/conv1x1.cpp:14~ultra96ms2_418/main_func.cpp:73</SourceLocation>
<SummaryOfLoopViolations>
<VITIS_LOOP_12_1_VITIS_LOOP_13_2_VITIS_LOOP_14_3>
<Name>VITIS_LOOP_12_1_VITIS_LOOP_13_2_VITIS_LOOP_14_3</Name>
<IssueType>-</IssueType>
<ViolationType>-</ViolationType>
<SourceLocation>ultra96ms2_418/conv1x1.cpp:12~ultra96ms2_418/main_func.cpp:73</SourceLocation>
</VITIS_LOOP_12_1_VITIS_LOOP_13_2_VITIS_LOOP_14_3>
</SummaryOfLoopViolations>
</SummaryOfViolations>
</PerformanceEstimates>

<AreaEstimates>
<Resources>
<DSP>3</DSP>
<FF>238</FF>
<LUT>458</LUT>
<BRAM_18K>0</BRAM_18K>
<URAM>0</URAM>
</Resources>
<AvailableResources>
<BRAM_18K>432</BRAM_18K>
<DSP>360</DSP>
<FF>141120</FF>
<LUT>70560</LUT>
<URAM>0</URAM>
</AvailableResources>
</AreaEstimates>

<InterfaceSummary>
<RtlPorts>
<name>ap_clk</name>
<Object>main_func_Pipeline_VITIS_LOOP_12_1_VITIS_LOOP_13_2_VITIS_LOOP_14_3</Object>
<Type>return value</Type>
<Scope></Scope>
<IOProtocol>ap_ctrl_hs</IOProtocol>
<IOConfig></IOConfig>
<Dir>in</Dir>
<Bits>1</Bits>
<Attribute>control</Attribute>
</RtlPorts>
<RtlPorts>
<name>ap_rst</name>
<Object>main_func_Pipeline_VITIS_LOOP_12_1_VITIS_LOOP_13_2_VITIS_LOOP_14_3</Object>
<Type>return value</Type>
<Scope></Scope>
<IOProtocol>ap_ctrl_hs</IOProtocol>
<IOConfig></IOConfig>
<Dir>in</Dir>
<Bits>1</Bits>
<Attribute>control</Attribute>
</RtlPorts>
<RtlPorts>
<name>ap_start</name>
<Object>main_func_Pipeline_VITIS_LOOP_12_1_VITIS_LOOP_13_2_VITIS_LOOP_14_3</Object>
<Type>return value</Type>
<Scope></Scope>
<IOProtocol>ap_ctrl_hs</IOProtocol>
<IOConfig></IOConfig>
<Dir>in</Dir>
<Bits>1</Bits>
<Attribute>control</Attribute>
</RtlPorts>
<RtlPorts>
<name>ap_done</name>
<Object>main_func_Pipeline_VITIS_LOOP_12_1_VITIS_LOOP_13_2_VITIS_LOOP_14_3</Object>
<Type>return value</Type>
<Scope></Scope>
<IOProtocol>ap_ctrl_hs</IOProtocol>
<IOConfig></IOConfig>
<Dir>out</Dir>
<Bits>1</Bits>
<Attribute>control</Attribute>
</RtlPorts>
<RtlPorts>
<name>ap_idle</name>
<Object>main_func_Pipeline_VITIS_LOOP_12_1_VITIS_LOOP_13_2_VITIS_LOOP_14_3</Object>
<Type>return value</Type>
<Scope></Scope>
<IOProtocol>ap_ctrl_hs</IOProtocol>
<IOConfig></IOConfig>
<Dir>out</Dir>
<Bits>1</Bits>
<Attribute>control</Attribute>
</RtlPorts>
<RtlPorts>
<name>ap_ready</name>
<Object>main_func_Pipeline_VITIS_LOOP_12_1_VITIS_LOOP_13_2_VITIS_LOOP_14_3</Object>
<Type>return value</Type>
<Scope></Scope>
<IOProtocol>ap_ctrl_hs</IOProtocol>
<IOConfig></IOConfig>
<Dir>out</Dir>
<Bits>1</Bits>
<Attribute>control</Attribute>
</RtlPorts>
<RtlPorts>
<name>bias_buf1x1_address0</name>
<Object>bias_buf1x1</Object>
<Type>array</Type>
<Scope>global</Scope>
<IOProtocol>ap_memory</IOProtocol>
<IOConfig></IOConfig>
<Dir>out</Dir>
<Bits>6</Bits>
<Attribute>address</Attribute>
</RtlPorts>
<RtlPorts>
<name>bias_buf1x1_ce0</name>
<Object>bias_buf1x1</Object>
<Type>array</Type>
<Scope>global</Scope>
<IOProtocol>ap_memory</IOProtocol>
<IOConfig></IOConfig>
<Dir>out</Dir>
<Bits>1</Bits>
<Attribute>control</Attribute>
</RtlPorts>
<RtlPorts>
<name>bias_buf1x1_q0</name>
<Object>bias_buf1x1</Object>
<Type>array</Type>
<Scope>global</Scope>
<IOProtocol>ap_memory</IOProtocol>
<IOConfig></IOConfig>
<Dir>in</Dir>
<Bits>16</Bits>
<Attribute>data</Attribute>
</RtlPorts>
<RtlPorts>
<name>weight_buf1x1_0_address0</name>
<Object>weight_buf1x1_0</Object>
<Type>array</Type>
<Scope>global</Scope>
<IOProtocol>ap_memory</IOProtocol>
<IOConfig></IOConfig>
<Dir>out</Dir>
<Bits>6</Bits>
<Attribute>address</Attribute>
</RtlPorts>
<RtlPorts>
<name>weight_buf1x1_0_ce0</name>
<Object>weight_buf1x1_0</Object>
<Type>array</Type>
<Scope>global</Scope>
<IOProtocol>ap_memory</IOProtocol>
<IOConfig></IOConfig>
<Dir>out</Dir>
<Bits>1</Bits>
<Attribute>control</Attribute>
</RtlPorts>
<RtlPorts>
<name>weight_buf1x1_0_q0</name>
<Object>weight_buf1x1_0</Object>
<Type>array</Type>
<Scope>global</Scope>
<IOProtocol>ap_memory</IOProtocol>
<IOConfig></IOConfig>
<Dir>in</Dir>
<Bits>16</Bits>
<Attribute>data</Attribute>
</RtlPorts>
<RtlPorts>
<name>weight_buf1x1_1_address0</name>
<Object>weight_buf1x1_1</Object>
<Type>array</Type>
<Scope>global</Scope>
<IOProtocol>ap_memory</IOProtocol>
<IOConfig></IOConfig>
<Dir>out</Dir>
<Bits>6</Bits>
<Attribute>address</Attribute>
</RtlPorts>
<RtlPorts>
<name>weight_buf1x1_1_ce0</name>
<Object>weight_buf1x1_1</Object>
<Type>array</Type>
<Scope>global</Scope>
<IOProtocol>ap_memory</IOProtocol>
<IOConfig></IOConfig>
<Dir>out</Dir>
<Bits>1</Bits>
<Attribute>control</Attribute>
</RtlPorts>
<RtlPorts>
<name>weight_buf1x1_1_q0</name>
<Object>weight_buf1x1_1</Object>
<Type>array</Type>
<Scope>global</Scope>
<IOProtocol>ap_memory</IOProtocol>
<IOConfig></IOConfig>
<Dir>in</Dir>
<Bits>16</Bits>
<Attribute>data</Attribute>
</RtlPorts>
<RtlPorts>
<name>weight_buf1x1_2_address0</name>
<Object>weight_buf1x1_2</Object>
<Type>array</Type>
<Scope>global</Scope>
<IOProtocol>ap_memory</IOProtocol>
<IOConfig></IOConfig>
<Dir>out</Dir>
<Bits>6</Bits>
<Attribute>address</Attribute>
</RtlPorts>
<RtlPorts>
<name>weight_buf1x1_2_ce0</name>
<Object>weight_buf1x1_2</Object>
<Type>array</Type>
<Scope>global</Scope>
<IOProtocol>ap_memory</IOProtocol>
<IOConfig></IOConfig>
<Dir>out</Dir>
<Bits>1</Bits>
<Attribute>control</Attribute>
</RtlPorts>
<RtlPorts>
<name>weight_buf1x1_2_q0</name>
<Object>weight_buf1x1_2</Object>
<Type>array</Type>
<Scope>global</Scope>
<IOProtocol>ap_memory</IOProtocol>
<IOConfig></IOConfig>
<Dir>in</Dir>
<Bits>16</Bits>
<Attribute>data</Attribute>
</RtlPorts>
<RtlPorts>
<name>outBuffer3x3_0_address0</name>
<Object>outBuffer3x3_0</Object>
<Type>array</Type>
<Scope>global</Scope>
<IOProtocol>ap_memory</IOProtocol>
<IOConfig></IOConfig>
<Dir>out</Dir>
<Bits>12</Bits>
<Attribute>address</Attribute>
</RtlPorts>
<RtlPorts>
<name>outBuffer3x3_0_ce0</name>
<Object>outBuffer3x3_0</Object>
<Type>array</Type>
<Scope>global</Scope>
<IOProtocol>ap_memory</IOProtocol>
<IOConfig></IOConfig>
<Dir>out</Dir>
<Bits>1</Bits>
<Attribute>control</Attribute>
</RtlPorts>
<RtlPorts>
<name>outBuffer3x3_0_q0</name>
<Object>outBuffer3x3_0</Object>
<Type>array</Type>
<Scope>global</Scope>
<IOProtocol>ap_memory</IOProtocol>
<IOConfig></IOConfig>
<Dir>in</Dir>
<Bits>16</Bits>
<Attribute>data</Attribute>
</RtlPorts>
<RtlPorts>
<name>outBuffer3x3_1_address0</name>
<Object>outBuffer3x3_1</Object>
<Type>array</Type>
<Scope>global</Scope>
<IOProtocol>ap_memory</IOProtocol>
<IOConfig></IOConfig>
<Dir>out</Dir>
<Bits>12</Bits>
<Attribute>address</Attribute>
</RtlPorts>
<RtlPorts>
<name>outBuffer3x3_1_ce0</name>
<Object>outBuffer3x3_1</Object>
<Type>array</Type>
<Scope>global</Scope>
<IOProtocol>ap_memory</IOProtocol>
<IOConfig></IOConfig>
<Dir>out</Dir>
<Bits>1</Bits>
<Attribute>control</Attribute>
</RtlPorts>
<RtlPorts>
<name>outBuffer3x3_1_q0</name>
<Object>outBuffer3x3_1</Object>
<Type>array</Type>
<Scope>global</Scope>
<IOProtocol>ap_memory</IOProtocol>
<IOConfig></IOConfig>
<Dir>in</Dir>
<Bits>16</Bits>
<Attribute>data</Attribute>
</RtlPorts>
<RtlPorts>
<name>outBuffer3x3_2_address0</name>
<Object>outBuffer3x3_2</Object>
<Type>array</Type>
<Scope>global</Scope>
<IOProtocol>ap_memory</IOProtocol>
<IOConfig></IOConfig>
<Dir>out</Dir>
<Bits>12</Bits>
<Attribute>address</Attribute>
</RtlPorts>
<RtlPorts>
<name>outBuffer3x3_2_ce0</name>
<Object>outBuffer3x3_2</Object>
<Type>array</Type>
<Scope>global</Scope>
<IOProtocol>ap_memory</IOProtocol>
<IOConfig></IOConfig>
<Dir>out</Dir>
<Bits>1</Bits>
<Attribute>control</Attribute>
</RtlPorts>
<RtlPorts>
<name>outBuffer3x3_2_q0</name>
<Object>outBuffer3x3_2</Object>
<Type>array</Type>
<Scope>global</Scope>
<IOProtocol>ap_memory</IOProtocol>
<IOConfig></IOConfig>
<Dir>in</Dir>
<Bits>16</Bits>
<Attribute>data</Attribute>
</RtlPorts>
<RtlPorts>
<name>outBuffer1x1_address0</name>
<Object>outBuffer1x1</Object>
<Type>array</Type>
<Scope>global</Scope>
<IOProtocol>ap_memory</IOProtocol>
<IOConfig></IOConfig>
<Dir>out</Dir>
<Bits>18</Bits>
<Attribute>address</Attribute>
</RtlPorts>
<RtlPorts>
<name>outBuffer1x1_ce0</name>
<Object>outBuffer1x1</Object>
<Type>array</Type>
<Scope>global</Scope>
<IOProtocol>ap_memory</IOProtocol>
<IOConfig></IOConfig>
<Dir>out</Dir>
<Bits>1</Bits>
<Attribute>control</Attribute>
</RtlPorts>
<RtlPorts>
<name>outBuffer1x1_we0</name>
<Object>outBuffer1x1</Object>
<Type>array</Type>
<Scope>global</Scope>
<IOProtocol>ap_memory</IOProtocol>
<IOConfig></IOConfig>
<Dir>out</Dir>
<Bits>1</Bits>
<Attribute>control</Attribute>
</RtlPorts>
<RtlPorts>
<name>outBuffer1x1_d0</name>
<Object>outBuffer1x1</Object>
<Type>array</Type>
<Scope>global</Scope>
<IOProtocol>ap_memory</IOProtocol>
<IOConfig></IOConfig>
<Dir>out</Dir>
<Bits>16</Bits>
<Attribute>data</Attribute>
</RtlPorts>
</InterfaceSummary>

</profile>
